calibrated_regression/__init__.py
calibrated_regression-1.0.2.dist-info/LICENSE
calibrated_regression-1.0.2.dist-info/METADATA
calibrated_regression-1.0.2.dist-info/WHEEL
calibrated_regression-1.0.2.dist-info/top_level.txt
calibrated_regression-1.0.2.dist-info/RECORD
