Metadata-Version: 2.1
Name: calibrated-regression
Version: 1.0.2
Summary: calibrated regression
Home-page: UNKNOWN
Author: Yu-Lun Liu
License: UNKNOWN
Platform: UNKNOWN
Classifier: Programming Language :: Python :: 3
Classifier: License :: OSI Approved :: GNU General Public License v3 (GPLv3)
Classifier: Operating System :: OS Independent
License-File: LICENSE
